{
  "token_id": "1001",
  "name": "Green Pea Flower",
  "description": "It takes 40 days from emergence to flower, when the temperature is in optimal range 12-18. ",
  "image": "ipfs://QmasyTnisRwa1h59bqydcuUTzrsUTx65NGXNmAnhDKtoQd/1-growth.png",
  "attributes": [
    { "Species" : "Dingwan 2" },
    { "Farmer's Name" : "Blue Man" },
    { "Seeding Date" : "15-March-2022" },
    { "Growth Stage" : "Emergence to Flower" },
    { "Growth period" : "40 days" },
    { "Temperature with in range" : "Yes" },
    { "Ripe Color" : "#fffdfa" }
  ]
}